genomon_sv/__init__.py
genomon_sv/annotationFunction.py
genomon_sv/arg_parser.py
genomon_sv/coveredRegions.py
genomon_sv/edlibFunction.py
genomon_sv/filterFunction.py
genomon_sv/mergeFunction.py
genomon_sv/parseFunction.py
genomon_sv/realignmentFunction.py
genomon_sv/run.py
genomon_sv/utils.py
genomon_sv-0.8.2.dist-info/LICENSE
genomon_sv-0.8.2.dist-info/METADATA
genomon_sv-0.8.2.dist-info/WHEEL
genomon_sv-0.8.2.dist-info/entry_points.txt
genomon_sv-0.8.2.dist-info/top_level.txt
genomon_sv-0.8.2.dist-info/RECORD
