Metadata-Version: 2.1
Name: genomon-sv
Version: 0.8.2
Summary: Python tools for detecting somatic structural variation from cancer genome sequencing data.
Home-page: https://github.com/friend1ws/GenomonSV
Author: Yuichi Shiraishi
Author-email: friend1ws@gamil.com
License: GPLv3
Platform: UNKNOWN
Classifier: Development Status :: 4 - Beta
Classifier: Intended Audience :: Science/Research
Classifier: License :: OSI Approved :: GNU General Public License v3 (GPLv3)
Classifier: Operating System :: Unix
Classifier: Programming Language :: Python :: 2.7
Classifier: Programming Language :: Python :: 3.6
Classifier: Programming Language :: Python :: 3.7
Classifier: Topic :: Scientific/Engineering :: Bio-Informatics
